{
  "idx": 109,
  "cite_key": "Sha25b",
  "title": "Next-generation neurotherapeutics: mechanistic insights on monoclonal antibodies in Alzheimer's disease.",
  "authors": "Akhil Sharma; T. Singh",
  "year": "2025",
  "pub_date": "2025-11-13",
  "journal": "Brain research",
  "abstract": "Monoclonal antibodies (mAbs) for Alzheimer's disease (AD) present a fundamental translational challenge, as demonstrated by amyloid-beta (Aβ)-targeting mAbs that successfully employed Fragment crystallizable gamma receptor (FcγR)/Immunoreceptor tyrosine-based activation motif (ITAM)-mediated microglial phagocytosis yet achieved only modest cognitive improvements while introducing significant Amyloid-related imaging abnormalities (ARIA) risk, thereby highlighting inherent single-therapy limitations. Building on these findings, tau-directed antibodies show preclinical promise by targeting pathological seeding and propagation, but face translational challenges including limited extracellular accessibility and variable efficacy across disease stages, necessitating expansion beyond single-target approaches. Consequently, the translational field is advancing toward innovative multi-mechanistic strategies, including synaptic restoration through anti-PrP and neurotrophic receptor agonists that provide functional benefits independent of plaque reduction, neuroinflammation modulation via anti-CD33 and complement inhibitors requiring careful patient selection due to variable outcomes, and emerging anti-TREM2 and anti-APOE4 mAbs enabling precision medicine tailored to individual genetic profiles. Importantly, comparative studies also reveal that combination therapies-especially dual Aβ/tau targeting-demonstrate superior synergistic effectiveness, driving next-generation engineering advances including Fc modifications that reduce ARIA risk, nanobodies/single-chain variable fragments (scFvs) with enhanced blood-brain barrier (BBB) penetration, cell-penetrating formats for intracellular tau access, and pH-sensitive glycoengineering for optimized tissue-specific binding. Ultimately, successful clinical translation depends on integrating biomarker-guided patient selection, optimized dosing strategies, and disease-stage-appropriate timing, with future progress anticipated through bispecific/multispecific antibodies targeting complementary pathways alongside personalized biomarker approaches, collectively providing realistic potential for achieving genuine neuroprotection and meaningful disease modification beyond symptomatic treatment in AD patients.",
  "citation_count": "2",
  "citations_per_year": "3.1",
  "doi": "10.1016/j.brainres.2025.150047",
  "url": "https://doi.org/10.1016/j.brainres.2025.150047",
  "slug": "sha25b-next-generation-neurotherapeutics-mechanistic-insights-on"
}